foca/__init__.py
foca/foca.py
foca/version.py
foca/api/__init__.py
foca/api/register_openapi.py
foca/config/__init__.py
foca/config/config_parser.py
foca/database/__init__.py
foca/database/register_mongodb.py
foca/errors/__init__.py
foca/errors/exceptions.py
foca/factories/__init__.py
foca/factories/celery_app.py
foca/factories/connexion_app.py
foca/models/__init__.py
foca/models/config.py
foca/security/__init__.py
foca/security/auth.py
foca/security/cors.py
foca/security/access_control/__init__.py
foca/security/access_control/access_control_server.py
foca/security/access_control/constants.py
foca/security/access_control/register_access_control.py
foca/security/access_control/api/__init__.py
foca/security/access_control/api/access-control-specs.yaml
foca/security/access_control/api/default_model.conf
foca/security/access_control/foca_casbin_adapter/__init__.py
foca/security/access_control/foca_casbin_adapter/adapter.py
foca/security/access_control/foca_casbin_adapter/casbin_rule.py
foca/utils/__init__.py
foca/utils/db.py
foca/utils/logging.py
foca/utils/misc.py
tests/__init__.py
tests/integration_tests.py
tests/mock_data.py
tests/test_foca.py
tests/test_version.py
tests/api/test_register_openapi.py
tests/api/controllers/__init__.py
tests/config/test_config_parser.py
tests/database/test_register_mongodb.py
tests/errors/test_errors.py
tests/factories/test_celery_app.py
tests/factories/test_connexion_app.py
tests/models/test_config.py
tests/security/test_auth.py
tests/security/test_cors.py
tests/security/access_control/test_access_control_server.py
tests/security/access_control/test_register_access_control.py
tests/security/access_control/foca_casbin_adapter/test_adapter.py
tests/security/access_control/foca_casbin_adapter/test_casbin_rule.py
tests/security/access_control/foca_casbin_adapter/test_files/rbac_model.conf
tests/security/access_control/foca_casbin_adapter/test_files/rbac_with_resources_roles.conf
tests/test_files/__init__.py
tests/test_files/conf_api.yaml
foca-0.13.0.dist-info/LICENSE
foca-0.13.0.dist-info/METADATA
foca-0.13.0.dist-info/WHEEL
foca-0.13.0.dist-info/top_level.txt
foca-0.13.0.dist-info/RECORD
