Metadata-Version: 2.1
Name: foca
Version: 0.13.0
Summary: Archetype for OpenAPI microservices based on Flask and Connexion
Home-page: https://github.com/elixir-cloud-aai/foca
Author: ELIXIR Cloud & AAI
Author-email: alexander.kanitz@alumni.ethz.ch
Maintainer: Alexander Kanitz
Maintainer-email: alexander.kanitz@alumnni.ethz.ch
Project-URL: Repository, https://github.com/elixir-cloud-aai/foca
Project-URL: ELIXIR Cloud & AAI, https://elixir-europe.github.io/cloud/
Project-URL: Tracker, https://github.com/elixir-cloud-aai/foca/issues
Keywords: rest api app openapi python microservice
Classifier: Development Status :: 3 - Alpha
Classifier: Environment :: Console
Classifier: Environment :: Web Environment
Classifier: Framework :: Flask
Classifier: Intended Audience :: Developers
Classifier: Intended Audience :: Information Technology
Classifier: Intended Audience :: System Administrators
Classifier: License :: OSI Approved :: Apache Software License
Classifier: Natural Language :: English
Classifier: Programming Language :: Python :: 3.9
Classifier: Programming Language :: Python :: 3.10
Classifier: Programming Language :: Python :: 3.11
Classifier: Topic :: Internet :: WWW/HTTP
Classifier: Topic :: System :: Systems Administration
Classifier: Topic :: Utilities
Classifier: Typing :: Typed
License-File: LICENSE
Requires-Dist: addict ~=2.2
Requires-Dist: celery ~=5.2
Requires-Dist: connexion ~=2.11
Requires-Dist: cryptography ~=42.0
Requires-Dist: Flask ~=2.2
Requires-Dist: flask-authz ~=2.5
Requires-Dist: Flask-Cors ~=4.0
Requires-Dist: Flask-PyMongo ~=2.3
Requires-Dist: pydantic ~=1.10
Requires-Dist: PyJWT ~=2.4
Requires-Dist: pymongo ~=4.7
Requires-Dist: PyYAML ~=6.0
Requires-Dist: requests ~=2.31
Requires-Dist: swagger-ui-bundle ~=0.0
Requires-Dist: toml ~=0.10
Requires-Dist: typing ~=3.7
Requires-Dist: Werkzeug ~=2.2
Provides-Extra: dev
Requires-Dist: coverage >=6.5 ; extra == 'dev'
Requires-Dist: flake8 >=6.1 ; extra == 'dev'
Requires-Dist: mongomock >=4.1 ; extra == 'dev'
Requires-Dist: mypy >=0.991 ; extra == 'dev'
Requires-Dist: mypy-extensions >=0.4.4 ; extra == 'dev'
Requires-Dist: pylint >=3.2 ; extra == 'dev'
Requires-Dist: pytest >=7.4 ; extra == 'dev'
Requires-Dist: python-semantic-release <8.2,>=7.34 ; extra == 'dev'
Requires-Dist: types-PyYAML ; extra == 'dev'
Requires-Dist: types-requests ; extra == 'dev'
Requires-Dist: types-setuptools ; extra == 'dev'
Requires-Dist: types-urllib3 ; extra == 'dev'
Provides-Extra: docs
Requires-Dist: Sphinx >=7.2 ; extra == 'docs'
Requires-Dist: readthedocs-sphinx-ext >=2.2 ; extra == 'docs'
Requires-Dist: sphinx-rtd-theme >=1.3 ; extra == 'docs'
